{"trial_id": "9dc0cac5ff13abf550436fb247df5492", "hyperparameters": {"space": [{"class_name": "Choice", "config": {"name": "activation", "default": "relu", "conditions": [], "values": ["relu", "tanh", "sigmoid"], "ordered": false}}, {"class_name": "Int", "config": {"name": "first_units", "default": null, "conditions": [], "min_value": 1, "max_value": 10, "step": 2, "sampling": null}}, {"class_name": "Int", "config": {"name": "num_layers", "default": null, "conditions": [], "min_value": 1, "max_value": 6, "step": 1, "sampling": null}}, {"class_name": "Int", "config": {"name": "units_0", "default": null, "conditions": [], "min_value": 1, "max_value": 10, "step": 2, "sampling": null}}, {"class_name": "Int", "config": {"name": "units_1", "default": null, "conditions": [], "min_value": 1, "max_value": 10, "step": 2, "sampling": null}}, {"class_name": "Int", "config": {"name": "units_2", "default": null, "conditions": [], "min_value": 1, "max_value": 10, "step": 2, "sampling": null}}, {"class_name": "Int", "config": {"name": "units_3", "default": null, "conditions": [], "min_value": 1, "max_value": 10, "step": 2, "sampling": null}}, {"class_name": "Int", "config": {"name": "units_4", "default": null, "conditions": [], "min_value": 1, "max_value": 10, "step": 2, "sampling": null}}, {"class_name": "Int", "config": {"name": "units_5", "default": null, "conditions": [], "min_value": 1, "max_value": 10, "step": 2, "sampling": null}}], "values": {"activation": "sigmoid", "first_units": 7, "num_layers": 1, "units_0": 7, "units_1": 5, "units_2": 5, "units_3": 1, "units_4": 5, "units_5": 9, "tuner/epochs": 7, "tuner/initial_epoch": 0, "tuner/bracket": 1, "tuner/round": 0}}, "metrics": {"metrics": {"loss": {"direction": "min", "observations": [{"value": [0.6273617148399353], "step": 0}]}, "accuracy": {"direction": "max", "observations": [{"value": [0.7319144010543823], "step": 0}]}, "val_loss": {"direction": "min", "observations": [{"value": [0.5821162462234497], "step": 0}]}, "val_accuracy": {"direction": "max", "observations": [{"value": [0.7290087342262268], "step": 0}]}}}, "score": 0.7290087342262268, "best_step": 0, "status": "COMPLETED"}